scholarly/__init__.py
scholarly/_navigator.py
scholarly/_proxy_generator.py
scholarly/_scholarly.py
scholarly/author_parser.py
scholarly/data_types.py
scholarly/publication_parser.py
scholarly-1.7.11.dist-info/LICENSE.txt
scholarly-1.7.11.dist-info/METADATA
scholarly-1.7.11.dist-info/WHEEL
scholarly-1.7.11.dist-info/top_level.txt
scholarly-1.7.11.dist-info/RECORD
