Metadata-Version: 2.1
Name: scholarly
Version: 1.7.11
Summary: Simple access to Google Scholar authors and citations
Home-page: https://github.com/scholarly-python-package/scholarly
Author: Steven A. Cholewiak, Panos Ipeirotis, Victor Silva, Arun Kannawadi
Author-email: steven@cholewiak.com, panos@stern.nyu.edu, vsilva@ualberta.ca, arunkannawadi@astro.princeton.edu
License: Unlicense
Keywords: Google Scholar,academics,citations
Classifier: Development Status :: 3 - Alpha
Classifier: Intended Audience :: Developers
Classifier: Intended Audience :: Science/Research
Classifier: Natural Language :: English
Classifier: Operating System :: OS Independent
Classifier: Programming Language :: Python :: 3
Classifier: Topic :: Software Development :: Libraries :: Python Modules
Provides-Extra: tor
License-File: LICENSE.txt
